<?xml version="1.0" encoding="UTF-8"?>
<con:soapui-project id="c7115f77-65cf-451b-a7a3-0cad5d4f0f17" activeEnvironment="Default" name="REST Project1" soapui-version="5.5.0" abortOnError="false" runType="SEQUENTIAL" xmlns:con="http://eviware.com/soapui/config"><con:settings/><con:interface xsi:type="con:RestService" id="ad8762ff-776e-401a-970e-c2d8aeaf429b" wadlVersion="http://wadl.dev.java.net/2009/02" name="https://restcountries.eu" type="rest" xmlns:xsi="http://www.w3.org/2001/XMLSchema-instance"><con:settings/><con:definitionCache type="TEXT" rootPart=""/><con:endpoints><con:endpoint>https://restcountries.eu</con:endpoint></con:endpoints><con:resource name="All" path="/rest/v2/{endpoint}" id="3a1fe773-d7b3-45fe-bfac-8b051a2064dc"><con:settings/><con:parameters><con:parameter><con:name>endpoint</con:name><con:style>TEMPLATE</con:style></con:parameter></con:parameters><con:method name="All 1" id="83191ed3-2248-4c34-a95f-3e87393470ca" method="GET"><con:settings/><con:parameters/><con:representation type="RESPONSE"><con:mediaType>application/json;charset=utf-8</con:mediaType><con:status>200</con:status><con:params/><con:element>Response</con:element></con:representation><con:representation type="FAULT"><con:mediaType xsi:nil="true"/><con:status>404</con:status><con:params/><con:element>data</con:element></con:representation><con:representation type="FAULT"><con:mediaType xsi:nil="true"/><con:status>404</con:status><con:params/><con:element>data</con:element></con:representation><con:representation type="FAULT"><con:mediaType xsi:nil="true"/><con:status>404</con:status><con:params/><con:element>data</con:element></con:representation><con:representation type="FAULT"><con:mediaType xsi:nil="true"/><con:status>404</con:status><con:params/><con:element>data</con:element></con:representation><con:representation type="FAULT"><con:mediaType xsi:nil="true"/><con:status>404</con:status><con:params/><con:element>data</con:element></con:representation><con:request name="Request 1" id="3941fdec-f635-4917-9d9e-140caff6b885" mediaType="application/json"><con:settings><con:setting id="com.eviware.soapui.impl.wsdl.WsdlRequest@request-headers">&lt;xml-fragment/></con:setting></con:settings><con:endpoint>https://restcountries.eu</con:endpoint><con:request/><con:originalUri>https://restcountries.eu/rest/v2/all</con:originalUri><con:credentials><con:authType>No Authorization</con:authType></con:credentials><con:jmsConfig JMSDeliveryMode="PERSISTENT"/><con:jmsPropertyConfig/><con:parameters><entry key="endpoint" value="INDIA" xmlns="http://eviware.com/soapui/config"/></con:parameters><con:parameterOrder><con:entry>endpoint</con:entry></con:parameterOrder></con:request></con:method></con:resource></con:interface><con:interface xsi:type="con:RestService" id="f5851f27-afac-4673-87de-1ba85f0ec48b" wadlVersion="http://wadl.dev.java.net/2009/02" name="https://restcountries.eu" type="rest" xmlns:xsi="http://www.w3.org/2001/XMLSchema-instance"><con:settings/><con:definitionCache type="TEXT" rootPart=""/><con:endpoints><con:endpoint>https://restcountries.eu</con:endpoint></con:endpoints><con:resource name="Aruba" path="/rest/v2/name/India/{fullText}" id="5bda6bf4-6068-4798-8914-c55961eed189"><con:settings/><con:parameters><con:parameter><con:name>fullText</con:name><con:style>TEMPLATE</con:style></con:parameter></con:parameters><con:method name="Contains_India" id="45d09155-54a5-4a4c-b4a1-2b0042a8fd22" method="GET"><con:settings/><con:parameters/><con:representation type="RESPONSE"><con:mediaType>application/json;charset=utf-8</con:mediaType><con:status>200</con:status><con:params/><con:element>Response</con:element></con:representation><con:representation type="FAULT"><con:mediaType>application/json;charset=utf-8</con:mediaType><con:status>404</con:status><con:params/><con:element xmlns:arub="https://restcountries.eu/rest/v2/name/aruba">arub:Fault</con:element></con:representation><con:representation type="FAULT"><con:mediaType xsi:nil="true"/><con:status>404</con:status><con:params/><con:element>data</con:element></con:representation><con:request name="Request 1" id="12c5791b-097b-49d2-be90-2bbd7357f052" mediaType="application/json"><con:settings><con:setting id="com.eviware.soapui.impl.wsdl.WsdlRequest@request-headers">&lt;xml-fragment/></con:setting></con:settings><con:endpoint>https://restcountries.eu</con:endpoint><con:request/><con:originalUri>https://restcountries.eu/rest/v2/name/aruba</con:originalUri><con:credentials><con:authType>No Authorization</con:authType></con:credentials><con:jmsConfig JMSDeliveryMode="PERSISTENT"/><con:jmsPropertyConfig/><con:parameters/><con:parameterOrder><con:entry>fullText</con:entry></con:parameterOrder></con:request></con:method></con:resource></con:interface><con:interface xsi:type="con:RestService" id="5fd34dd5-d784-4cbc-ba98-8552259887c3" wadlVersion="http://wadl.dev.java.net/2009/02" name="https://restcountries.eu" type="rest" xmlns:xsi="http://www.w3.org/2001/XMLSchema-instance"><con:settings/><con:definitionCache/><con:endpoints><con:endpoint>https://restcountries.eu</con:endpoint></con:endpoints><con:resource name="All" path="/rest/v2/all" id="134dd5cb-7b2d-406b-8388-ddbad82ee90a"><con:settings/><con:parameters/><con:method name="All 1" id="b0484a79-a933-4751-b2c0-54de644f5270" method="GET"><con:settings/><con:parameters/><con:request name="Request 1" id="0035b627-3da0-44d9-bfcb-8466c06426c8" mediaType="application/json"><con:settings/><con:endpoint>https://restcountries.eu</con:endpoint><con:request/><con:credentials><con:authType>No Authorization</con:authType></con:credentials><con:jmsConfig JMSDeliveryMode="PERSISTENT"/><con:jmsPropertyConfig/><con:parameters/></con:request></con:method></con:resource></con:interface><con:interface xsi:type="con:WsdlInterface" id="b9339bf9-b086-4546-9b38-4584ab16b030" wsaVersion="NONE" name="CountryInfoServiceSoapBinding" type="wsdl" bindingName="{http://www.oorsprong.org/websamples.countryinfo}CountryInfoServiceSoapBinding" soapVersion="1_1" anonymous="optional" definition="http://webservices.oorsprong.org/websamples.countryinfo/CountryInfoService.wso?WSDL" xmlns:xsi="http://www.w3.org/2001/XMLSchema-instance"><con:settings><con:setting id="CreateWsdlDocumentationAction@report-directory">C:\Users\home\Desktop</con:setting></con:settings><con:definitionCache type="TEXT" rootPart="http://webservices.oorsprong.org/websamples.countryinfo/CountryInfoService.wso?WSDL"><con:part><con:url>http://webservices.oorsprong.org/websamples.countryinfo/CountryInfoService.wso?WSDL</con:url><con:content><![CDATA[<definitions name="CountryInfoService" targetNamespace="http://www.oorsprong.org/websamples.countryinfo" xmlns="http://schemas.xmlsoap.org/wsdl/" xmlns:xs="http://www.w3.org/2001/XMLSchema" xmlns:soap="http://schemas.xmlsoap.org/wsdl/soap/" xmlns:soap12="http://schemas.xmlsoap.org/wsdl/soap12/" xmlns:tns="http://www.oorsprong.org/websamples.countryinfo">
  <types>
    <xs:schema elementFormDefault="qualified" targetNamespace="http://www.oorsprong.org/websamples.countryinfo">
      <xs:complexType name="tContinent">
        <xs:sequence>
          <xs:element name="sCode" type="xs:string"/>
          <xs:element name="sName" type="xs:string"/>
        </xs:sequence>
      </xs:complexType>
      <xs:complexType name="tCurrency">
        <xs:sequence>
          <xs:element name="sISOCode" type="xs:string"/>
          <xs:element name="sName" type="xs:string"/>
        </xs:sequence>
      </xs:complexType>
      <xs:complexType name="tCountryCodeAndName">
        <xs:sequence>
          <xs:element name="sISOCode" type="xs:string"/>
          <xs:element name="sName" type="xs:string"/>
        </xs:sequence>
      </xs:complexType>
      <xs:complexType name="tCountryCodeAndNameGroupedByContinent">
        <xs:sequence>
          <xs:element name="Continent" type="tns:tContinent"/>
          <xs:element name="CountryCodeAndNames" type="tns:ArrayOftCountryCodeAndName"/>
        </xs:sequence>
      </xs:complexType>
      <xs:complexType name="tCountryInfo">
        <xs:sequence>
          <xs:element name="sISOCode" type="xs:string"/>
          <xs:element name="sName" type="xs:string"/>
          <xs:element name="sCapitalCity" type="xs:string"/>
          <xs:element name="sPhoneCode" type="xs:string"/>
          <xs:element name="sContinentCode" type="xs:string"/>
          <xs:element name="sCurrencyISOCode" type="xs:string"/>
          <xs:element name="sCountryFlag" type="xs:string"/>
          <xs:element name="Languages" type="tns:ArrayOftLanguage"/>
        </xs:sequence>
      </xs:complexType>
      <xs:complexType name="tLanguage">
        <xs:sequence>
          <xs:element name="sISOCode" type="xs:string"/>
          <xs:element name="sName" type="xs:string"/>
        </xs:sequence>
      </xs:complexType>
      <xs:complexType name="ArrayOftCountryCodeAndName">
        <xs:sequence>
          <xs:element name="tCountryCodeAndName" type="tns:tCountryCodeAndName" minOccurs="0" maxOccurs="unbounded" nillable="true"/>
        </xs:sequence>
      </xs:complexType>
      <xs:complexType name="ArrayOftLanguage">
        <xs:sequence>
          <xs:element name="tLanguage" type="tns:tLanguage" minOccurs="0" maxOccurs="unbounded" nillable="true"/>
        </xs:sequence>
      </xs:complexType>
      <xs:complexType name="ArrayOftContinent">
        <xs:sequence>
          <xs:element name="tContinent" type="tns:tContinent" minOccurs="0" maxOccurs="unbounded" nillable="true"/>
        </xs:sequence>
      </xs:complexType>
      <xs:complexType name="ArrayOftCurrency">
        <xs:sequence>
          <xs:element name="tCurrency" type="tns:tCurrency" minOccurs="0" maxOccurs="unbounded" nillable="true"/>
        </xs:sequence>
      </xs:complexType>
      <xs:complexType name="ArrayOftCountryCodeAndNameGroupedByContinent">
        <xs:sequence>
          <xs:element name="tCountryCodeAndNameGroupedByContinent" type="tns:tCountryCodeAndNameGroupedByContinent" minOccurs="0" maxOccurs="unbounded" nillable="true"/>
        </xs:sequence>
      </xs:complexType>
      <xs:complexType name="ArrayOftCountryInfo">
        <xs:sequence>
          <xs:element name="tCountryInfo" type="tns:tCountryInfo" minOccurs="0" maxOccurs="unbounded" nillable="true"/>
        </xs:sequence>
      </xs:complexType>
      <xs:element name="ListOfContinentsByName">
        <xs:complexType>
          <xs:sequence/>
        </xs:complexType>
      </xs:element>
      <xs:element name="ListOfContinentsByNameResponse">
        <xs:complexType>
          <xs:sequence>
            <xs:element name="ListOfContinentsByNameResult" type="tns:ArrayOftContinent"/>
          </xs:sequence>
        </xs:complexType>
      </xs:element>
      <xs:element name="ListOfContinentsByCode">
        <xs:complexType>
          <xs:sequence/>
        </xs:complexType>
      </xs:element>
      <xs:element name="ListOfContinentsByCodeResponse">
        <xs:complexType>
          <xs:sequence>
            <xs:element name="ListOfContinentsByCodeResult" type="tns:ArrayOftContinent"/>
          </xs:sequence>
        </xs:complexType>
      </xs:element>
      <xs:element name="ListOfCurrenciesByName">
        <xs:complexType>
          <xs:sequence/>
        </xs:complexType>
      </xs:element>
      <xs:element name="ListOfCurrenciesByNameResponse">
        <xs:complexType>
          <xs:sequence>
            <xs:element name="ListOfCurrenciesByNameResult" type="tns:ArrayOftCurrency"/>
          </xs:sequence>
        </xs:complexType>
      </xs:element>
      <xs:element name="ListOfCurrenciesByCode">
        <xs:complexType>
          <xs:sequence/>
        </xs:complexType>
      </xs:element>
      <xs:element name="ListOfCurrenciesByCodeResponse">
        <xs:complexType>
          <xs:sequence>
            <xs:element name="ListOfCurrenciesByCodeResult" type="tns:ArrayOftCurrency"/>
          </xs:sequence>
        </xs:complexType>
      </xs:element>
      <xs:element name="CurrencyName">
        <xs:complexType>
          <xs:sequence>
            <xs:element name="sCurrencyISOCode" type="xs:string"/>
          </xs:sequence>
        </xs:complexType>
      </xs:element>
      <xs:element name="CurrencyNameResponse">
        <xs:complexType>
          <xs:sequence>
            <xs:element name="CurrencyNameResult" type="xs:string"/>
          </xs:sequence>
        </xs:complexType>
      </xs:element>
      <xs:element name="ListOfCountryNamesByCode">
        <xs:complexType>
          <xs:sequence/>
        </xs:complexType>
      </xs:element>
      <xs:element name="ListOfCountryNamesByCodeResponse">
        <xs:complexType>
          <xs:sequence>
            <xs:element name="ListOfCountryNamesByCodeResult" type="tns:ArrayOftCountryCodeAndName"/>
          </xs:sequence>
        </xs:complexType>
      </xs:element>
      <xs:element name="ListOfCountryNamesByName">
        <xs:complexType>
          <xs:sequence/>
        </xs:complexType>
      </xs:element>
      <xs:element name="ListOfCountryNamesByNameResponse">
        <xs:complexType>
          <xs:sequence>
            <xs:element name="ListOfCountryNamesByNameResult" type="tns:ArrayOftCountryCodeAndName"/>
          </xs:sequence>
        </xs:complexType>
      </xs:element>
      <xs:element name="ListOfCountryNamesGroupedByContinent">
        <xs:complexType>
          <xs:sequence/>
        </xs:complexType>
      </xs:element>
      <xs:element name="ListOfCountryNamesGroupedByContinentResponse">
        <xs:complexType>
          <xs:sequence>
            <xs:element name="ListOfCountryNamesGroupedByContinentResult" type="tns:ArrayOftCountryCodeAndNameGroupedByContinent"/>
          </xs:sequence>
        </xs:complexType>
      </xs:element>
      <xs:element name="CountryName">
        <xs:complexType>
          <xs:sequence>
            <xs:element name="sCountryISOCode" type="xs:string"/>
          </xs:sequence>
        </xs:complexType>
      </xs:element>
      <xs:element name="CountryNameResponse">
        <xs:complexType>
          <xs:sequence>
            <xs:element name="CountryNameResult" type="xs:string"/>
          </xs:sequence>
        </xs:complexType>
      </xs:element>
      <xs:element name="CountryISOCode">
        <xs:complexType>
          <xs:sequence>
            <xs:element name="sCountryName" type="xs:string"/>
          </xs:sequence>
        </xs:complexType>
      </xs:element>
      <xs:element name="CountryISOCodeResponse">
        <xs:complexType>
          <xs:sequence>
            <xs:element name="CountryISOCodeResult" type="xs:string"/>
          </xs:sequence>
        </xs:complexType>
      </xs:element>
      <xs:element name="CapitalCity">
        <xs:complexType>
          <xs:sequence>
            <xs:element name="sCountryISOCode" type="xs:string"/>
          </xs:sequence>
        </xs:complexType>
      </xs:element>
      <xs:element name="CapitalCityResponse">
        <xs:complexType>
          <xs:sequence>
            <xs:element name="CapitalCityResult" type="xs:string"/>
          </xs:sequence>
        </xs:complexType>
      </xs:element>
      <xs:element name="CountryCurrency">
        <xs:complexType>
          <xs:sequence>
            <xs:element name="sCountryISOCode" type="xs:string"/>
          </xs:sequence>
        </xs:complexType>
      </xs:element>
      <xs:element name="CountryCurrencyResponse">
        <xs:complexType>
          <xs:sequence>
            <xs:element name="CountryCurrencyResult" type="tns:tCurrency"/>
          </xs:sequence>
        </xs:complexType>
      </xs:element>
      <xs:element name="CountryFlag">
        <xs:complexType>
          <xs:sequence>
            <xs:element name="sCountryISOCode" type="xs:string"/>
          </xs:sequence>
        </xs:complexType>
      </xs:element>
      <xs:element name="CountryFlagResponse">
        <xs:complexType>
          <xs:sequence>
            <xs:element name="CountryFlagResult" type="xs:string"/>
          </xs:sequence>
        </xs:complexType>
      </xs:element>
      <xs:element name="CountryIntPhoneCode">
        <xs:complexType>
          <xs:sequence>
            <xs:element name="sCountryISOCode" type="xs:string"/>
          </xs:sequence>
        </xs:complexType>
      </xs:element>
      <xs:element name="CountryIntPhoneCodeResponse">
        <xs:complexType>
          <xs:sequence>
            <xs:element name="CountryIntPhoneCodeResult" type="xs:string"/>
          </xs:sequence>
        </xs:complexType>
      </xs:element>
      <xs:element name="FullCountryInfo">
        <xs:complexType>
          <xs:sequence>
            <xs:element name="sCountryISOCode" type="xs:string"/>
          </xs:sequence>
        </xs:complexType>
      </xs:element>
      <xs:element name="FullCountryInfoResponse">
        <xs:complexType>
          <xs:sequence>
            <xs:element name="FullCountryInfoResult" type="tns:tCountryInfo"/>
          </xs:sequence>
        </xs:complexType>
      </xs:element>
      <xs:element name="FullCountryInfoAllCountries">
        <xs:complexType>
          <xs:sequence/>
        </xs:complexType>
      </xs:element>
      <xs:element name="FullCountryInfoAllCountriesResponse">
        <xs:complexType>
          <xs:sequence>
            <xs:element name="FullCountryInfoAllCountriesResult" type="tns:ArrayOftCountryInfo"/>
          </xs:sequence>
        </xs:complexType>
      </xs:element>
      <xs:element name="CountriesUsingCurrency">
        <xs:complexType>
          <xs:sequence>
            <xs:element name="sISOCurrencyCode" type="xs:string"/>
          </xs:sequence>
        </xs:complexType>
      </xs:element>
      <xs:element name="CountriesUsingCurrencyResponse">
        <xs:complexType>
          <xs:sequence>
            <xs:element name="CountriesUsingCurrencyResult" type="tns:ArrayOftCountryCodeAndName"/>
          </xs:sequence>
        </xs:complexType>
      </xs:element>
      <xs:element name="ListOfLanguagesByName">
        <xs:complexType>
          <xs:sequence/>
        </xs:complexType>
      </xs:element>
      <xs:element name="ListOfLanguagesByNameResponse">
        <xs:complexType>
          <xs:sequence>
            <xs:element name="ListOfLanguagesByNameResult" type="tns:ArrayOftLanguage"/>
          </xs:sequence>
        </xs:complexType>
      </xs:element>
      <xs:element name="ListOfLanguagesByCode">
        <xs:complexType>
          <xs:sequence/>
        </xs:complexType>
      </xs:element>
      <xs:element name="ListOfLanguagesByCodeResponse">
        <xs:complexType>
          <xs:sequence>
            <xs:element name="ListOfLanguagesByCodeResult" type="tns:ArrayOftLanguage"/>
          </xs:sequence>
        </xs:complexType>
      </xs:element>
      <xs:element name="LanguageName">
        <xs:complexType>
          <xs:sequence>
            <xs:element name="sISOCode" type="xs:string"/>
          </xs:sequence>
        </xs:complexType>
      </xs:element>
      <xs:element name="LanguageNameResponse">
        <xs:complexType>
          <xs:sequence>
            <xs:element name="LanguageNameResult" type="xs:string"/>
          </xs:sequence>
        </xs:complexType>
      </xs:element>
      <xs:element name="LanguageISOCode">
        <xs:complexType>
          <xs:sequence>
            <xs:element name="sLanguageName" type="xs:string"/>
          </xs:sequence>
        </xs:complexType>
      </xs:element>
      <xs:element name="LanguageISOCodeResponse">
        <xs:complexType>
          <xs:sequence>
            <xs:element name="LanguageISOCodeResult" type="xs:string"/>
          </xs:sequence>
        </xs:complexType>
      </xs:element>
    </xs:schema>
  </types>
  <message name="ListOfContinentsByNameSoapRequest">
    <part name="parameters" element="tns:ListOfContinentsByName"/>
  </message>
  <message name="ListOfContinentsByNameSoapResponse">
    <part name="parameters" element="tns:ListOfContinentsByNameResponse"/>
  </message>
  <message name="ListOfContinentsByCodeSoapRequest">
    <part name="parameters" element="tns:ListOfContinentsByCode"/>
  </message>
  <message name="ListOfContinentsByCodeSoapResponse">
    <part name="parameters" element="tns:ListOfContinentsByCodeResponse"/>
  </message>
  <message name="ListOfCurrenciesByNameSoapRequest">
    <part name="parameters" element="tns:ListOfCurrenciesByName"/>
  </message>
  <message name="ListOfCurrenciesByNameSoapResponse">
    <part name="parameters" element="tns:ListOfCurrenciesByNameResponse"/>
  </message>
  <message name="ListOfCurrenciesByCodeSoapRequest">
    <part name="parameters" element="tns:ListOfCurrenciesByCode"/>
  </message>
  <message name="ListOfCurrenciesByCodeSoapResponse">
    <part name="parameters" element="tns:ListOfCurrenciesByCodeResponse"/>
  </message>
  <message name="CurrencyNameSoapRequest">
    <part name="parameters" element="tns:CurrencyName"/>
  </message>
  <message name="CurrencyNameSoapResponse">
    <part name="parameters" element="tns:CurrencyNameResponse"/>
  </message>
  <message name="ListOfCountryNamesByCodeSoapRequest">
    <part name="parameters" element="tns:ListOfCountryNamesByCode"/>
  </message>
  <message name="ListOfCountryNamesByCodeSoapResponse">
    <part name="parameters" element="tns:ListOfCountryNamesByCodeResponse"/>
  </message>
  <message name="ListOfCountryNamesByNameSoapRequest">
    <part name="parameters" element="tns:ListOfCountryNamesByName"/>
  </message>
  <message name="ListOfCountryNamesByNameSoapResponse">
    <part name="parameters" element="tns:ListOfCountryNamesByNameResponse"/>
  </message>
  <message name="ListOfCountryNamesGroupedByContinentSoapRequest">
    <part name="parameters" element="tns:ListOfCountryNamesGroupedByContinent"/>
  </message>
  <message name="ListOfCountryNamesGroupedByContinentSoapResponse">
    <part name="parameters" element="tns:ListOfCountryNamesGroupedByContinentResponse"/>
  </message>
  <message name="CountryNameSoapRequest">
    <part name="parameters" element="tns:CountryName"/>
  </message>
  <message name="CountryNameSoapResponse">
    <part name="parameters" element="tns:CountryNameResponse"/>
  </message>
  <message name="CountryISOCodeSoapRequest">
    <part name="parameters" element="tns:CountryISOCode"/>
  </message>
  <message name="CountryISOCodeSoapResponse">
    <part name="parameters" element="tns:CountryISOCodeResponse"/>
  </message>
  <message name="CapitalCitySoapRequest">
    <part name="parameters" element="tns:CapitalCity"/>
  </message>
  <message name="CapitalCitySoapResponse">
    <part name="parameters" element="tns:CapitalCityResponse"/>
  </message>
  <message name="CountryCurrencySoapRequest">
    <part name="parameters" element="tns:CountryCurrency"/>
  </message>
  <message name="CountryCurrencySoapResponse">
    <part name="parameters" element="tns:CountryCurrencyResponse"/>
  </message>
  <message name="CountryFlagSoapRequest">
    <part name="parameters" element="tns:CountryFlag"/>
  </message>
  <message name="CountryFlagSoapResponse">
    <part name="parameters" element="tns:CountryFlagResponse"/>
  </message>
  <message name="CountryIntPhoneCodeSoapRequest">
    <part name="parameters" element="tns:CountryIntPhoneCode"/>
  </message>
  <message name="CountryIntPhoneCodeSoapResponse">
    <part name="parameters" element="tns:CountryIntPhoneCodeResponse"/>
  </message>
  <message name="FullCountryInfoSoapRequest">
    <part name="parameters" element="tns:FullCountryInfo"/>
  </message>
  <message name="FullCountryInfoSoapResponse">
    <part name="parameters" element="tns:FullCountryInfoResponse"/>
  </message>
  <message name="FullCountryInfoAllCountriesSoapRequest">
    <part name="parameters" element="tns:FullCountryInfoAllCountries"/>
  </message>
  <message name="FullCountryInfoAllCountriesSoapResponse">
    <part name="parameters" element="tns:FullCountryInfoAllCountriesResponse"/>
  </message>
  <message name="CountriesUsingCurrencySoapRequest">
    <part name="parameters" element="tns:CountriesUsingCurrency"/>
  </message>
  <message name="CountriesUsingCurrencySoapResponse">
    <part name="parameters" element="tns:CountriesUsingCurrencyResponse"/>
  </message>
  <message name="ListOfLanguagesByNameSoapRequest">
    <part name="parameters" element="tns:ListOfLanguagesByName"/>
  </message>
  <message name="ListOfLanguagesByNameSoapResponse">
    <part name="parameters" element="tns:ListOfLanguagesByNameResponse"/>
  </message>
  <message name="ListOfLanguagesByCodeSoapRequest">
    <part name="parameters" element="tns:ListOfLanguagesByCode"/>
  </message>
  <message name="ListOfLanguagesByCodeSoapResponse">
    <part name="parameters" element="tns:ListOfLanguagesByCodeResponse"/>
  </message>
  <message name="LanguageNameSoapRequest">
    <part name="parameters" element="tns:LanguageName"/>
  </message>
  <message name="LanguageNameSoapResponse">
    <part name="parameters" element="tns:LanguageNameResponse"/>
  </message>
  <message name="LanguageISOCodeSoapRequest">
    <part name="parameters" element="tns:LanguageISOCode"/>
  </message>
  <message name="LanguageISOCodeSoapResponse">
    <part name="parameters" element="tns:LanguageISOCodeResponse"/>
  </message>
  <portType name="CountryInfoServiceSoapType">
    <operation name="ListOfContinentsByName">
      <documentation>Returns a list of continents ordered by name.</documentation>
      <input message="tns:ListOfContinentsByNameSoapRequest"/>
      <output message="tns:ListOfContinentsByNameSoapResponse"/>
    </operation>
    <operation name="ListOfContinentsByCode">
      <documentation>Returns a list of continents ordered by code.</documentation>
      <input message="tns:ListOfContinentsByCodeSoapRequest"/>
      <output message="tns:ListOfContinentsByCodeSoapResponse"/>
    </operation>
    <operation name="ListOfCurrenciesByName">
      <documentation>Returns a list of currencies ordered by name.</documentation>
      <input message="tns:ListOfCurrenciesByNameSoapRequest"/>
      <output message="tns:ListOfCurrenciesByNameSoapResponse"/>
    </operation>
    <operation name="ListOfCurrenciesByCode">
      <documentation>Returns a list of currencies ordered by code.</documentation>
      <input message="tns:ListOfCurrenciesByCodeSoapRequest"/>
      <output message="tns:ListOfCurrenciesByCodeSoapResponse"/>
    </operation>
    <operation name="CurrencyName">
      <documentation>Returns the name of the currency (if found)</documentation>
      <input message="tns:CurrencyNameSoapRequest"/>
      <output message="tns:CurrencyNameSoapResponse"/>
    </operation>
    <operation name="ListOfCountryNamesByCode">
      <documentation>Returns a list of all stored counties ordered by ISO code</documentation>
      <input message="tns:ListOfCountryNamesByCodeSoapRequest"/>
      <output message="tns:ListOfCountryNamesByCodeSoapResponse"/>
    </operation>
    <operation name="ListOfCountryNamesByName">
      <documentation>Returns a list of all stored counties ordered by country name</documentation>
      <input message="tns:ListOfCountryNamesByNameSoapRequest"/>
      <output message="tns:ListOfCountryNamesByNameSoapResponse"/>
    </operation>
    <operation name="ListOfCountryNamesGroupedByContinent">
      <documentation>Returns a list of all stored counties grouped per continent</documentation>
      <input message="tns:ListOfCountryNamesGroupedByContinentSoapRequest"/>
      <output message="tns:ListOfCountryNamesGroupedByContinentSoapResponse"/>
    </operation>
    <operation name="CountryName">
      <documentation>Searches the database for a country by the passed ISO country code</documentation>
      <input message="tns:CountryNameSoapRequest"/>
      <output message="tns:CountryNameSoapResponse"/>
    </operation>
    <operation name="CountryISOCode">
      <documentation>This function tries to found a country based on the passed country name.</documentation>
      <input message="tns:CountryISOCodeSoapRequest"/>
      <output message="tns:CountryISOCodeSoapResponse"/>
    </operation>
    <operation name="CapitalCity">
      <documentation>Returns the  name of the captial city for the passed country code</documentation>
      <input message="tns:CapitalCitySoapRequest"/>
      <output message="tns:CapitalCitySoapResponse"/>
    </operation>
    <operation name="CountryCurrency">
      <documentation>Returns the currency ISO code and name for the passed country ISO code</documentation>
      <input message="tns:CountryCurrencySoapRequest"/>
      <output message="tns:CountryCurrencySoapResponse"/>
    </operation>
    <operation name="CountryFlag">
      <documentation>Returns a link to a picture of the country flag</documentation>
      <input message="tns:CountryFlagSoapRequest"/>
      <output message="tns:CountryFlagSoapResponse"/>
    </operation>
    <operation name="CountryIntPhoneCode">
      <documentation>Returns the internation phone code for the passed ISO country code</documentation>
      <input message="tns:CountryIntPhoneCodeSoapRequest"/>
      <output message="tns:CountryIntPhoneCodeSoapResponse"/>
    </operation>
    <operation name="FullCountryInfo">
      <documentation>Returns a struct with all the stored country information. Pass the ISO country code</documentation>
      <input message="tns:FullCountryInfoSoapRequest"/>
      <output message="tns:FullCountryInfoSoapResponse"/>
    </operation>
    <operation name="FullCountryInfoAllCountries">
      <documentation>Returns an array with all countries and all the language information stored</documentation>
      <input message="tns:FullCountryInfoAllCountriesSoapRequest"/>
      <output message="tns:FullCountryInfoAllCountriesSoapResponse"/>
    </operation>
    <operation name="CountriesUsingCurrency">
      <documentation>Returns a list of all countries that use the same currency code. Pass a ISO currency code</documentation>
      <input message="tns:CountriesUsingCurrencySoapRequest"/>
      <output message="tns:CountriesUsingCurrencySoapResponse"/>
    </operation>
    <operation name="ListOfLanguagesByName">
      <documentation>Returns an array of languages ordered by name</documentation>
      <input message="tns:ListOfLanguagesByNameSoapRequest"/>
      <output message="tns:ListOfLanguagesByNameSoapResponse"/>
    </operation>
    <operation name="ListOfLanguagesByCode">
      <documentation>Returns an array of languages ordered by code</documentation>
      <input message="tns:ListOfLanguagesByCodeSoapRequest"/>
      <output message="tns:ListOfLanguagesByCodeSoapResponse"/>
    </operation>
    <operation name="LanguageName">
      <documentation>Find a language name based on the passed ISO language code</documentation>
      <input message="tns:LanguageNameSoapRequest"/>
      <output message="tns:LanguageNameSoapResponse"/>
    </operation>
    <operation name="LanguageISOCode">
      <documentation>Find a language ISO code based on the passed language name</documentation>
      <input message="tns:LanguageISOCodeSoapRequest"/>
      <output message="tns:LanguageISOCodeSoapResponse"/>
    </operation>
  </portType>
  <binding name="CountryInfoServiceSoapBinding" type="tns:CountryInfoServiceSoapType">
    <soap:binding style="document" transport="http://schemas.xmlsoap.org/soap/http"/>
    <operation name="ListOfContinentsByName">
      <soap:operation soapAction="" style="document"/>
      <input>
        <soap:body use="literal"/>
      </input>
      <output>
        <soap:body use="literal"/>
      </output>
    </operation>
    <operation name="ListOfContinentsByCode">
      <soap:operation soapAction="" style="document"/>
      <input>
        <soap:body use="literal"/>
      </input>
      <output>
        <soap:body use="literal"/>
      </output>
    </operation>
    <operation name="ListOfCurrenciesByName">
      <soap:operation soapAction="" style="document"/>
      <input>
        <soap:body use="literal"/>
      </input>
      <output>
        <soap:body use="literal"/>
      </output>
    </operation>
    <operation name="ListOfCurrenciesByCode">
      <soap:operation soapAction="" style="document"/>
      <input>
        <soap:body use="literal"/>
      </input>
      <output>
        <soap:body use="literal"/>
      </output>
    </operation>
    <operation name="CurrencyName">
      <soap:operation soapAction="" style="document"/>
      <input>
        <soap:body use="literal"/>
      </input>
      <output>
        <soap:body use="literal"/>
      </output>
    </operation>
    <operation name="ListOfCountryNamesByCode">
      <soap:operation soapAction="" style="document"/>
      <input>
        <soap:body use="literal"/>
      </input>
      <output>
        <soap:body use="literal"/>
      </output>
    </operation>
    <operation name="ListOfCountryNamesByName">
      <soap:operation soapAction="" style="document"/>
      <input>
        <soap:body use="literal"/>
      </input>
      <output>
        <soap:body use="literal"/>
      </output>
    </operation>
    <operation name="ListOfCountryNamesGroupedByContinent">
      <soap:operation soapAction="" style="document"/>
      <input>
        <soap:body use="literal"/>
      </input>
      <output>
        <soap:body use="literal"/>
      </output>
    </operation>
    <operation name="CountryName">
      <soap:operation soapAction="" style="document"/>
      <input>
        <soap:body use="literal"/>
      </input>
      <output>
        <soap:body use="literal"/>
      </output>
    </operation>
    <operation name="CountryISOCode">
      <soap:operation soapAction="" style="document"/>
      <input>
        <soap:body use="literal"/>
      </input>
      <output>
        <soap:body use="literal"/>
      </output>
    </operation>
    <operation name="CapitalCity">
      <soap:operation soapAction="" style="document"/>
      <input>
        <soap:body use="literal"/>
      </input>
      <output>
        <soap:body use="literal"/>
      </output>
    </operation>
    <operation name="CountryCurrency">
      <soap:operation soapAction="" style="document"/>
      <input>
        <soap:body use="literal"/>
      </input>
      <output>
        <soap:body use="literal"/>
      </output>
    </operation>
    <operation name="CountryFlag">
      <soap:operation soapAction="" style="document"/>
      <input>
        <soap:body use="literal"/>
      </input>
      <output>
        <soap:body use="literal"/>
      </output>
    </operation>
    <operation name="CountryIntPhoneCode">
      <soap:operation soapAction="" style="document"/>
      <input>
        <soap:body use="literal"/>
      </input>
      <output>
        <soap:body use="literal"/>
      </output>
    </operation>
    <operation name="FullCountryInfo">
      <soap:operation soapAction="" style="document"/>
      <input>
        <soap:body use="literal"/>
      </input>
      <output>
        <soap:body use="literal"/>
      </output>
    </operation>
    <operation name="FullCountryInfoAllCountries">
      <soap:operation soapAction="" style="document"/>
      <input>
        <soap:body use="literal"/>
      </input>
      <output>
        <soap:body use="literal"/>
      </output>
    </operation>
    <operation name="CountriesUsingCurrency">
      <soap:operation soapAction="" style="document"/>
      <input>
        <soap:body use="literal"/>
      </input>
      <output>
        <soap:body use="literal"/>
      </output>
    </operation>
    <operation name="ListOfLanguagesByName">
      <soap:operation soapAction="" style="document"/>
      <input>
        <soap:body use="literal"/>
      </input>
      <output>
        <soap:body use="literal"/>
      </output>
    </operation>
    <operation name="ListOfLanguagesByCode">
      <soap:operation soapAction="" style="document"/>
      <input>
        <soap:body use="literal"/>
      </input>
      <output>
        <soap:body use="literal"/>
      </output>
    </operation>
    <operation name="LanguageName">
      <soap:operation soapAction="" style="document"/>
      <input>
        <soap:body use="literal"/>
      </input>
      <output>
        <soap:body use="literal"/>
      </output>
    </operation>
    <operation name="LanguageISOCode">
      <soap:operation soapAction="" style="document"/>
      <input>
        <soap:body use="literal"/>
      </input>
      <output>
        <soap:body use="literal"/>
      </output>
    </operation>
  </binding>
  <binding name="CountryInfoServiceSoapBinding12" type="tns:CountryInfoServiceSoapType">
    <soap12:binding style="document" transport="http://schemas.xmlsoap.org/soap/http"/>
    <operation name="ListOfContinentsByName">
      <soap12:operation soapAction="" style="document"/>
      <input>
        <soap12:body use="literal"/>
      </input>
      <output>
        <soap12:body use="literal"/>
      </output>
    </operation>
    <operation name="ListOfContinentsByCode">
      <soap12:operation soapAction="" style="document"/>
      <input>
        <soap12:body use="literal"/>
      </input>
      <output>
        <soap12:body use="literal"/>
      </output>
    </operation>
    <operation name="ListOfCurrenciesByName">
      <soap12:operation soapAction="" style="document"/>
      <input>
        <soap12:body use="literal"/>
      </input>
      <output>
        <soap12:body use="literal"/>
      </output>
    </operation>
    <operation name="ListOfCurrenciesByCode">
      <soap12:operation soapAction="" style="document"/>
      <input>
        <soap12:body use="literal"/>
      </input>
      <output>
        <soap12:body use="literal"/>
      </output>
    </operation>
    <operation name="CurrencyName">
      <soap12:operation soapAction="" style="document"/>
      <input>
        <soap12:body use="literal"/>
      </input>
      <output>
        <soap12:body use="literal"/>
      </output>
    </operation>
    <operation name="ListOfCountryNamesByCode">
      <soap12:operation soapAction="" style="document"/>
      <input>
        <soap12:body use="literal"/>
      </input>
      <output>
        <soap12:body use="literal"/>
      </output>
    </operation>
    <operation name="ListOfCountryNamesByName">
      <soap12:operation soapAction="" style="document"/>
      <input>
        <soap12:body use="literal"/>
      </input>
      <output>
        <soap12:body use="literal"/>
      </output>
    </operation>
    <operation name="ListOfCountryNamesGroupedByContinent">
      <soap12:operation soapAction="" style="document"/>
      <input>
        <soap12:body use="literal"/>
      </input>
      <output>
        <soap12:body use="literal"/>
      </output>
    </operation>
    <operation name="CountryName">
      <soap12:operation soapAction="" style="document"/>
      <input>
        <soap12:body use="literal"/>
      </input>
      <output>
        <soap12:body use="literal"/>
      </output>
    </operation>
    <operation name="CountryISOCode">
      <soap12:operation soapAction="" style="document"/>
      <input>
        <soap12:body use="literal"/>
      </input>
      <output>
        <soap12:body use="literal"/>
      </output>
    </operation>
    <operation name="CapitalCity">
      <soap12:operation soapAction="" style="document"/>
      <input>
        <soap12:body use="literal"/>
      </input>
      <output>
        <soap12:body use="literal"/>
      </output>
    </operation>
    <operation name="CountryCurrency">
      <soap12:operation soapAction="" style="document"/>
      <input>
        <soap12:body use="literal"/>
      </input>
      <output>
        <soap12:body use="literal"/>
      </output>
    </operation>
    <operation name="CountryFlag">
      <soap12:operation soapAction="" style="document"/>
      <input>
        <soap12:body use="literal"/>
      </input>
      <output>
        <soap12:body use="literal"/>
      </output>
    </operation>
    <operation name="CountryIntPhoneCode">
      <soap12:operation soapAction="" style="document"/>
      <input>
        <soap12:body use="literal"/>
      </input>
      <output>
        <soap12:body use="literal"/>
      </output>
    </operation>
    <operation name="FullCountryInfo">
      <soap12:operation soapAction="" style="document"/>
      <input>
        <soap12:body use="literal"/>
      </input>
      <output>
        <soap12:body use="literal"/>
      </output>
    </operation>
    <operation name="FullCountryInfoAllCountries">
      <soap12:operation soapAction="" style="document"/>
      <input>
        <soap12:body use="literal"/>
      </input>
      <output>
        <soap12:body use="literal"/>
      </output>
    </operation>
    <operation name="CountriesUsingCurrency">
      <soap12:operation soapAction="" style="document"/>
      <input>
        <soap12:body use="literal"/>
      </input>
      <output>
        <soap12:body use="literal"/>
      </output>
    </operation>
    <operation name="ListOfLanguagesByName">
      <soap12:operation soapAction="" style="document"/>
      <input>
        <soap12:body use="literal"/>
      </input>
      <output>
        <soap12:body use="literal"/>
      </output>
    </operation>
    <operation name="ListOfLanguagesByCode">
      <soap12:operation soapAction="" style="document"/>
      <input>
        <soap12:body use="literal"/>
      </input>
      <output>
        <soap12:body use="literal"/>
      </output>
    </operation>
    <operation name="LanguageName">
      <soap12:operation soapAction="" style="document"/>
      <input>
        <soap12:body use="literal"/>
      </input>
      <output>
        <soap12:body use="literal"/>
      </output>
    </operation>
    <operation name="LanguageISOCode">
      <soap12:operation soapAction="" style="document"/>
      <input>
        <soap12:body use="literal"/>
      </input>
      <output>
        <soap12:body use="literal"/>
      </output>
    </operation>
  </binding>
  <service name="CountryInfoService">
    <documentation>This DataFlex Web Service opens up country information. 2 letter ISO codes are used for Country code. There are functions to retrieve the used Currency, Language, Capital City, Continent and Telephone code.</documentation>
    <port name="CountryInfoServiceSoap" binding="tns:CountryInfoServiceSoapBinding">
      <soap:address location="http://webservices.oorsprong.org/websamples.countryinfo/CountryInfoService.wso"/>
    </port>
    <port name="CountryInfoServiceSoap12" binding="tns:CountryInfoServiceSoapBinding12">
      <soap12:address location="http://webservices.oorsprong.org/websamples.countryinfo/CountryInfoService.wso"/>
    </port>
  </service>
</definitions>]]></con:content><con:type>http://schemas.xmlsoap.org/wsdl/</con:type></con:part></con:definitionCache><con:endpoints><con:endpoint>http://webservices.oorsprong.org/websamples.countryinfo/CountryInfoService.wso</con:endpoint></con:endpoints><con:operation id="1f8c1cb6-3435-41f0-a005-d04ba817482e" isOneWay="false" action="" name="CapitalCity" bindingOperationName="CapitalCity" type="Request-Response" inputName="" receivesAttachments="false" sendsAttachments="false" anonymous="optional"><con:settings/><con:call id="8bf9e566-d1d2-465a-9cce-8b6d237edeb9" name="Request 1"><con:settings><con:setting id="com.eviware.soapui.impl.wsdl.WsdlRequest@request-headers">&lt;xml-fragment/></con:setting></con:settings><con:encoding>UTF-8</con:encoding><con:endpoint>http://webservices.oorsprong.org/websamples.countryinfo/CountryInfoService.wso</con:endpoint><con:request><![CDATA[<soapenv:Envelope xmlns:soapenv="http://schemas.xmlsoap.org/soap/envelope/" xmlns:web="http://www.oorsprong.org/websamples.countryinfo">\r
   <soapenv:Header/>\r
   <soapenv:Body>\r
      <web:CapitalCity>\r
         <web:sCountryISOCode>IN</web:sCountryISOCode>\r
      </web:CapitalCity>\r
   </soapenv:Body>\r
</soapenv:Envelope>]]></con:request><con:credentials><con:authType>No Authorization</con:authType></con:credentials><con:jmsConfig JMSDeliveryMode="PERSISTENT"/><con:jmsPropertyConfig/><con:wsaConfig mustUnderstand="NONE" version="200508" action="http://www.oorsprong.org/websamples.countryinfo/CountryInfoServiceSoapType/CapitalCityRequest"/><con:wsrmConfig version="1.2"/></con:call></con:operation><con:operation id="f956fe41-ecee-44e6-848b-da85493e4ec5" isOneWay="false" action="" name="CountriesUsingCurrency" bindingOperationName="CountriesUsingCurrency" type="Request-Response" inputName="" receivesAttachments="false" sendsAttachments="false" anonymous="optional"><con:settings/><con:call id="22ef39c2-8774-46c7-ba90-8a5764ccf3ae" name="Request 1"><con:settings/><con:encoding>UTF-8</con:encoding><con:endpoint>http://webservices.oorsprong.org/websamples.countryinfo/CountryInfoService.wso</con:endpoint><con:request><![CDATA[<soapenv:Envelope xmlns:soapenv="http://schemas.xmlsoap.org/soap/envelope/" xmlns:web="http://www.oorsprong.org/websamples.countryinfo">\r
   <soapenv:Header/>\r
   <soapenv:Body>\r
      <web:CountriesUsingCurrency>\r
         <web:sISOCurrencyCode>?</web:sISOCurrencyCode>\r
      </web:CountriesUsingCurrency>\r
   </soapenv:Body>\r
</soapenv:Envelope>]]></con:request><con:jmsConfig JMSDeliveryMode="PERSISTENT"/><con:wsaConfig mustUnderstand="NONE" version="200508" action="http://www.oorsprong.org/websamples.countryinfo/CountryInfoServiceSoapType/CountriesUsingCurrencyRequest"/></con:call></con:operation><con:operation id="58d8adbb-4905-49d2-9091-e08e9766e7ad" isOneWay="false" action="" name="CountryCurrency" bindingOperationName="CountryCurrency" type="Request-Response" inputName="" receivesAttachments="false" sendsAttachments="false" anonymous="optional"><con:settings/><con:call id="a0ff7e82-7094-4170-8ea4-55cfc68797b0" name="Request 1"><con:settings><con:setting id="com.eviware.soapui.impl.wsdl.WsdlRequest@request-headers">&lt;xml-fragment/></con:setting></con:settings><con:encoding>UTF-8</con:encoding><con:endpoint>http://webservices.oorsprong.org/websamples.countryinfo/CountryInfoService.wso</con:endpoint><con:request><![CDATA[<soapenv:Envelope xmlns:soapenv="http://schemas.xmlsoap.org/soap/envelope/" xmlns:web="http://www.oorsprong.org/websamples.countryinfo">\r
   <soapenv:Header/>\r
   <soapenv:Body>\r
      <web:CountryCurrency>\r
         <web:sCountryISOCode>IN</web:sCountryISOCode>\r
      </web:CountryCurrency>\r
   </soapenv:Body>\r
</soapenv:Envelope>]]></con:request><con:credentials><con:authType>No Authorization</con:authType></con:credentials><con:jmsConfig JMSDeliveryMode="PERSISTENT"/><con:jmsPropertyConfig/><con:wsaConfig mustUnderstand="NONE" version="200508" action="http://www.oorsprong.org/websamples.countryinfo/CountryInfoServiceSoapType/CountryCurrencyRequest"/><con:wsrmConfig version="1.2"/></con:call></con:operation><con:operation id="8726f0ea-2dea-496e-b19e-31bcd8a73b76" isOneWay="false" action="" name="CountryFlag" bindingOperationName="CountryFlag" type="Request-Response" inputName="" receivesAttachments="false" sendsAttachments="false" anonymous="optional"><con:settings/><con:call id="b37db4f6-5f05-475c-b4b2-dac111e6880a" name="Request 1"><con:settings/><con:encoding>UTF-8</con:encoding><con:endpoint>http://webservices.oorsprong.org/websamples.countryinfo/CountryInfoService.wso</con:endpoint><con:request><![CDATA[<soapenv:Envelope xmlns:soapenv="http://schemas.xmlsoap.org/soap/envelope/" xmlns:web="http://www.oorsprong.org/websamples.countryinfo">\r
   <soapenv:Header/>\r
   <soapenv:Body>\r
      <web:CountryFlag>\r
         <web:sCountryISOCode>?</web:sCountryISOCode>\r
      </web:CountryFlag>\r
   </soapenv:Body>\r
</soapenv:Envelope>]]></con:request><con:jmsConfig JMSDeliveryMode="PERSISTENT"/><con:wsaConfig mustUnderstand="NONE" version="200508" action="http://www.oorsprong.org/websamples.countryinfo/CountryInfoServiceSoapType/CountryFlagRequest"/></con:call></con:operation><con:operation id="1ab87345-cea6-4975-828e-1e5c7e4aa9fb" isOneWay="false" action="" name="CountryIntPhoneCode" bindingOperationName="CountryIntPhoneCode" type="Request-Response" inputName="" receivesAttachments="false" sendsAttachments="false" anonymous="optional"><con:settings/><con:call id="ec130d6f-bac2-4d1b-b15f-32c214944c2c" name="Request 1"><con:settings/><con:encoding>UTF-8</con:encoding><con:endpoint>http://webservices.oorsprong.org/websamples.countryinfo/CountryInfoService.wso</con:endpoint><con:request><![CDATA[<soapenv:Envelope xmlns:soapenv="http://schemas.xmlsoap.org/soap/envelope/" xmlns:web="http://www.oorsprong.org/websamples.countryinfo">\r
   <soapenv:Header/>\r
   <soapenv:Body>\r
      <web:CountryIntPhoneCode>\r
         <web:sCountryISOCode>?</web:sCountryISOCode>\r
      </web:CountryIntPhoneCode>\r
   </soapenv:Body>\r
</soapenv:Envelope>]]></con:request><con:jmsConfig JMSDeliveryMode="PERSISTENT"/><con:wsaConfig mustUnderstand="NONE" version="200508" action="http://www.oorsprong.org/websamples.countryinfo/CountryInfoServiceSoapType/CountryIntPhoneCodeRequest"/></con:call></con:operation><con:operation id="32c0a755-4b44-4e43-9a8a-8d2287c4cbad" isOneWay="false" action="" name="CountryISOCode" bindingOperationName="CountryISOCode" type="Request-Response" inputName="" receivesAttachments="false" sendsAttachments="false" anonymous="optional"><con:settings/><con:call id="1fcd36f2-b5c4-4784-befa-df8730ed965e" name="Request 1"><con:settings/><con:encoding>UTF-8</con:encoding><con:endpoint>http://webservices.oorsprong.org/websamples.countryinfo/CountryInfoService.wso</con:endpoint><con:request><![CDATA[<soapenv:Envelope xmlns:soapenv="http://schemas.xmlsoap.org/soap/envelope/" xmlns:web="http://www.oorsprong.org/websamples.countryinfo">\r
   <soapenv:Header/>\r
   <soapenv:Body>\r
      <web:CountryISOCode>\r
         <web:sCountryName>?</web:sCountryName>\r
      </web:CountryISOCode>\r
   </soapenv:Body>\r
</soapenv:Envelope>]]></con:request><con:jmsConfig JMSDeliveryMode="PERSISTENT"/><con:wsaConfig mustUnderstand="NONE" version="200508" action="http://www.oorsprong.org/websamples.countryinfo/CountryInfoServiceSoapType/CountryISOCodeRequest"/></con:call></con:operation><con:operation id="96768b9a-332d-4dfb-9869-067d70bc39b9" isOneWay="false" action="" name="CountryName" bindingOperationName="CountryName" type="Request-Response" inputName="" receivesAttachments="false" sendsAttachments="false" anonymous="optional"><con:settings/><con:call id="d6ca94ca-bfaf-4040-9e01-bde980c6890c" name="Request 1"><con:settings/><con:encoding>UTF-8</con:encoding><con:endpoint>http://webservices.oorsprong.org/websamples.countryinfo/CountryInfoService.wso</con:endpoint><con:request><![CDATA[<soapenv:Envelope xmlns:soapenv="http://schemas.xmlsoap.org/soap/envelope/" xmlns:web="http://www.oorsprong.org/websamples.countryinfo">\r
   <soapenv:Header/>\r
   <soapenv:Body>\r
      <web:CountryName>\r
         <web:sCountryISOCode>?</web:sCountryISOCode>\r
      </web:CountryName>\r
   </soapenv:Body>\r
</soapenv:Envelope>]]></con:request><con:jmsConfig JMSDeliveryMode="PERSISTENT"/><con:wsaConfig mustUnderstand="NONE" version="200508" action="http://www.oorsprong.org/websamples.countryinfo/CountryInfoServiceSoapType/CountryNameRequest"/></con:call></con:operation><con:operation id="2414aa73-6195-40bc-9797-1410dd68670f" isOneWay="false" action="" name="CurrencyName" bindingOperationName="CurrencyName" type="Request-Response" inputName="" receivesAttachments="false" sendsAttachments="false" anonymous="optional"><con:settings/><con:call id="7591bda1-9254-414a-8ddd-384c0fcc6d8d" name="Request 1"><con:settings/><con:encoding>UTF-8</con:encoding><con:endpoint>http://webservices.oorsprong.org/websamples.countryinfo/CountryInfoService.wso</con:endpoint><con:request><![CDATA[<soapenv:Envelope xmlns:soapenv="http://schemas.xmlsoap.org/soap/envelope/" xmlns:web="http://www.oorsprong.org/websamples.countryinfo">\r
   <soapenv:Header/>\r
   <soapenv:Body>\r
      <web:CurrencyName>\r
         <web:sCurrencyISOCode>?</web:sCurrencyISOCode>\r
      </web:CurrencyName>\r
   </soapenv:Body>\r
</soapenv:Envelope>]]></con:request><con:jmsConfig JMSDeliveryMode="PERSISTENT"/><con:wsaConfig mustUnderstand="NONE" version="200508" action="http://www.oorsprong.org/websamples.countryinfo/CountryInfoServiceSoapType/CurrencyNameRequest"/></con:call></con:operation><con:operation id="4741527e-71b9-4ea6-8723-b347fd5e61e0" isOneWay="false" action="" name="FullCountryInfo" bindingOperationName="FullCountryInfo" type="Request-Response" inputName="" receivesAttachments="false" sendsAttachments="false" anonymous="optional"><con:settings/><con:call id="21174a1c-865b-4a4c-9e53-56596beb9281" name="Request 1"><con:settings/><con:encoding>UTF-8</con:encoding><con:endpoint>http://webservices.oorsprong.org/websamples.countryinfo/CountryInfoService.wso</con:endpoint><con:request><![CDATA[<soapenv:Envelope xmlns:soapenv="http://schemas.xmlsoap.org/soap/envelope/" xmlns:web="http://www.oorsprong.org/websamples.countryinfo">\r
   <soapenv:Header/>\r
   <soapenv:Body>\r
      <web:FullCountryInfo>\r
         <web:sCountryISOCode>?</web:sCountryISOCode>\r
      </web:FullCountryInfo>\r
   </soapenv:Body>\r
</soapenv:Envelope>]]></con:request><con:jmsConfig JMSDeliveryMode="PERSISTENT"/><con:wsaConfig mustUnderstand="NONE" version="200508" action="http://www.oorsprong.org/websamples.countryinfo/CountryInfoServiceSoapType/FullCountryInfoRequest"/></con:call></con:operation><con:operation id="0281f7ec-ce5f-49aa-b355-f2252cfa4b97" isOneWay="false" action="" name="FullCountryInfoAllCountries" bindingOperationName="FullCountryInfoAllCountries" type="Request-Response" inputName="" receivesAttachments="false" sendsAttachments="false" anonymous="optional"><con:settings/><con:call id="3b9b0d1b-1c1c-4f90-ad62-008de6797b94" name="Request 1"><con:settings/><con:encoding>UTF-8</con:encoding><con:endpoint>http://webservices.oorsprong.org/websamples.countryinfo/CountryInfoService.wso</con:endpoint><con:request><![CDATA[<soapenv:Envelope xmlns:soapenv="http://schemas.xmlsoap.org/soap/envelope/" xmlns:web="http://www.oorsprong.org/websamples.countryinfo">\r
   <soapenv:Header/>\r
   <soapenv:Body>\r
      <web:FullCountryInfoAllCountries/>\r
   </soapenv:Body>\r
</soapenv:Envelope>]]></con:request><con:jmsConfig JMSDeliveryMode="PERSISTENT"/><con:wsaConfig mustUnderstand="NONE" version="200508" action="http://www.oorsprong.org/websamples.countryinfo/CountryInfoServiceSoapType/FullCountryInfoAllCountriesRequest"/></con:call></con:operation><con:operation id="f4d128c0-a5e4-48f8-b468-7751224d9af9" isOneWay="false" action="" name="LanguageISOCode" bindingOperationName="LanguageISOCode" type="Request-Response" inputName="" receivesAttachments="false" sendsAttachments="false" anonymous="optional"><con:settings/><con:call id="8b163eeb-9104-4cae-b873-e9fbaea344c0" name="Request 1"><con:settings/><con:encoding>UTF-8</con:encoding><con:endpoint>http://webservices.oorsprong.org/websamples.countryinfo/CountryInfoService.wso</con:endpoint><con:request><![CDATA[<soapenv:Envelope xmlns:soapenv="http://schemas.xmlsoap.org/soap/envelope/" xmlns:web="http://www.oorsprong.org/websamples.countryinfo">\r
   <soapenv:Header/>\r
   <soapenv:Body>\r
      <web:LanguageISOCode>\r
         <web:sLanguageName>?</web:sLanguageName>\r
      </web:LanguageISOCode>\r
   </soapenv:Body>\r
</soapenv:Envelope>]]></con:request><con:jmsConfig JMSDeliveryMode="PERSISTENT"/><con:wsaConfig mustUnderstand="NONE" version="200508" action="http://www.oorsprong.org/websamples.countryinfo/CountryInfoServiceSoapType/LanguageISOCodeRequest"/></con:call></con:operation><con:operation id="817e9962-1f9c-4b9c-9b9b-1104d0120be7" isOneWay="false" action="" name="LanguageName" bindingOperationName="LanguageName" type="Request-Response" inputName="" receivesAttachments="false" sendsAttachments="false" anonymous="optional"><con:settings/><con:call id="e385bb09-31f0-40d1-8bcd-31d66ed610a5" name="Request 1"><con:settings/><con:encoding>UTF-8</con:encoding><con:endpoint>http://webservices.oorsprong.org/websamples.countryinfo/CountryInfoService.wso</con:endpoint><con:request><![CDATA[<soapenv:Envelope xmlns:soapenv="http://schemas.xmlsoap.org/soap/envelope/" xmlns:web="http://www.oorsprong.org/websamples.countryinfo">\r
   <soapenv:Header/>\r
   <soapenv:Body>\r
      <web:LanguageName>\r
         <web:sISOCode>?</web:sISOCode>\r
      </web:LanguageName>\r
   </soapenv:Body>\r
</soapenv:Envelope>]]></con:request><con:jmsConfig JMSDeliveryMode="PERSISTENT"/><con:wsaConfig mustUnderstand="NONE" version="200508" action="http://www.oorsprong.org/websamples.countryinfo/CountryInfoServiceSoapType/LanguageNameRequest"/></con:call></con:operation><con:operation id="e59d3c31-24e6-45e5-a335-64ad9bb06a07" isOneWay="false" action="" name="ListOfContinentsByCode" bindingOperationName="ListOfContinentsByCode" type="Request-Response" inputName="" receivesAttachments="false" sendsAttachments="false" anonymous="optional"><con:settings/><con:call id="ffbaa489-0e0d-4be5-99e6-61eb2214b52c" name="Request 1"><con:settings/><con:encoding>UTF-8</con:encoding><con:endpoint>http://webservices.oorsprong.org/websamples.countryinfo/CountryInfoService.wso</con:endpoint><con:request><![CDATA[<soapenv:Envelope xmlns:soapenv="http://schemas.xmlsoap.org/soap/envelope/" xmlns:web="http://www.oorsprong.org/websamples.countryinfo">\r
   <soapenv:Header/>\r
   <soapenv:Body>\r
      <web:ListOfContinentsByCode/>\r
   </soapenv:Body>\r
</soapenv:Envelope>]]></con:request><con:jmsConfig JMSDeliveryMode="PERSISTENT"/><con:wsaConfig mustUnderstand="NONE" version="200508" action="http://www.oorsprong.org/websamples.countryinfo/CountryInfoServiceSoapType/ListOfContinentsByCodeRequest"/></con:call></con:operation><con:operation id="0bd509b6-b57e-4e42-93b4-d78227041bb9" isOneWay="false" action="" name="ListOfContinentsByName" bindingOperationName="ListOfContinentsByName" type="Request-Response" inputName="" receivesAttachments="false" sendsAttachments="false" anonymous="optional"><con:settings/><con:call id="88e8ce95-1f28-4c0f-b04b-d1f7b08cb0ef" name="Request 1"><con:settings/><con:encoding>UTF-8</con:encoding><con:endpoint>http://webservices.oorsprong.org/websamples.countryinfo/CountryInfoService.wso</con:endpoint><con:request><![CDATA[<soapenv:Envelope xmlns:soapenv="http://schemas.xmlsoap.org/soap/envelope/" xmlns:web="http://www.oorsprong.org/websamples.countryinfo">\r
   <soapenv:Header/>\r
   <soapenv:Body>\r
      <web:ListOfContinentsByName/>\r
   </soapenv:Body>\r
</soapenv:Envelope>]]></con:request><con:jmsConfig JMSDeliveryMode="PERSISTENT"/><con:wsaConfig mustUnderstand="NONE" version="200508" action="http://www.oorsprong.org/websamples.countryinfo/CountryInfoServiceSoapType/ListOfContinentsByNameRequest"/></con:call></con:operation><con:operation id="ad12b782-2f79-46d1-b03f-e6c0bf23f8fc" isOneWay="false" action="" name="ListOfCountryNamesByCode" bindingOperationName="ListOfCountryNamesByCode" type="Request-Response" inputName="" receivesAttachments="false" sendsAttachments="false" anonymous="optional"><con:settings/><con:call id="06e778d7-64b4-4817-9bec-464b9682b9f9" name="Request 1"><con:settings/><con:encoding>UTF-8</con:encoding><con:endpoint>http://webservices.oorsprong.org/websamples.countryinfo/CountryInfoService.wso</con:endpoint><con:request><![CDATA[<soapenv:Envelope xmlns:soapenv="http://schemas.xmlsoap.org/soap/envelope/" xmlns:web="http://www.oorsprong.org/websamples.countryinfo">\r
   <soapenv:Header/>\r
   <soapenv:Body>\r
      <web:ListOfCountryNamesByCode/>\r
   </soapenv:Body>\r
</soapenv:Envelope>]]></con:request><con:jmsConfig JMSDeliveryMode="PERSISTENT"/><con:wsaConfig mustUnderstand="NONE" version="200508" action="http://www.oorsprong.org/websamples.countryinfo/CountryInfoServiceSoapType/ListOfCountryNamesByCodeRequest"/></con:call></con:operation><con:operation id="a2e9b654-8f5a-487f-b806-ab2d0664cef6" isOneWay="false" action="" name="ListOfCountryNamesByName" bindingOperationName="ListOfCountryNamesByName" type="Request-Response" inputName="" receivesAttachments="false" sendsAttachments="false" anonymous="optional"><con:settings/><con:call id="fe580c6b-979d-43e4-b0a1-94978b58cdcf" name="Request 1"><con:settings/><con:encoding>UTF-8</con:encoding><con:endpoint>http://webservices.oorsprong.org/websamples.countryinfo/CountryInfoService.wso</con:endpoint><con:request><![CDATA[<soapenv:Envelope xmlns:soapenv="http://schemas.xmlsoap.org/soap/envelope/" xmlns:web="http://www.oorsprong.org/websamples.countryinfo">\r
   <soapenv:Header/>\r
   <soapenv:Body>\r
      <web:ListOfCountryNamesByName/>\r
   </soapenv:Body>\r
</soapenv:Envelope>]]></con:request><con:jmsConfig JMSDeliveryMode="PERSISTENT"/><con:wsaConfig mustUnderstand="NONE" version="200508" action="http://www.oorsprong.org/websamples.countryinfo/CountryInfoServiceSoapType/ListOfCountryNamesByNameRequest"/></con:call></con:operation><con:operation id="3888743b-dd04-4f15-ba75-009e81e7cbe6" isOneWay="false" action="" name="ListOfCountryNamesGroupedByContinent" bindingOperationName="ListOfCountryNamesGroupedByContinent" type="Request-Response" inputName="" receivesAttachments="false" sendsAttachments="false" anonymous="optional"><con:settings/><con:call id="a67507ab-7d8f-43ad-96bc-8e189797db74" name="Request 1"><con:settings/><con:encoding>UTF-8</con:encoding><con:endpoint>http://webservices.oorsprong.org/websamples.countryinfo/CountryInfoService.wso</con:endpoint><con:request><![CDATA[<soapenv:Envelope xmlns:soapenv="http://schemas.xmlsoap.org/soap/envelope/" xmlns:web="http://www.oorsprong.org/websamples.countryinfo">\r
   <soapenv:Header/>\r
   <soapenv:Body>\r
      <web:ListOfCountryNamesGroupedByContinent/>\r
   </soapenv:Body>\r
</soapenv:Envelope>]]></con:request><con:jmsConfig JMSDeliveryMode="PERSISTENT"/><con:wsaConfig mustUnderstand="NONE" version="200508" action="http://www.oorsprong.org/websamples.countryinfo/CountryInfoServiceSoapType/ListOfCountryNamesGroupedByContinentRequest"/></con:call></con:operation><con:operation id="5bc6004f-1856-438e-9f39-764d284a9884" isOneWay="false" action="" name="ListOfCurrenciesByCode" bindingOperationName="ListOfCurrenciesByCode" type="Request-Response" inputName="" receivesAttachments="false" sendsAttachments="false" anonymous="optional"><con:settings/><con:call id="76a2d70b-bfe1-435f-bf2c-487f60503fff" name="Request 1"><con:settings/><con:encoding>UTF-8</con:encoding><con:endpoint>http://webservices.oorsprong.org/websamples.countryinfo/CountryInfoService.wso</con:endpoint><con:request><![CDATA[<soapenv:Envelope xmlns:soapenv="http://schemas.xmlsoap.org/soap/envelope/" xmlns:web="http://www.oorsprong.org/websamples.countryinfo">\r
   <soapenv:Header/>\r
   <soapenv:Body>\r
      <web:ListOfCurrenciesByCode/>\r
   </soapenv:Body>\r
</soapenv:Envelope>]]></con:request><con:jmsConfig JMSDeliveryMode="PERSISTENT"/><con:wsaConfig mustUnderstand="NONE" version="200508" action="http://www.oorsprong.org/websamples.countryinfo/CountryInfoServiceSoapType/ListOfCurrenciesByCodeRequest"/></con:call></con:operation><con:operation id="f1b29c91-71ea-43b8-95e1-ac62df82a1e3" isOneWay="false" action="" name="ListOfCurrenciesByName" bindingOperationName="ListOfCurrenciesByName" type="Request-Response" inputName="" receivesAttachments="false" sendsAttachments="false" anonymous="optional"><con:settings/><con:call id="ea3dcc3f-a23d-4c82-8d92-182e95622202" name="Request 1"><con:settings/><con:encoding>UTF-8</con:encoding><con:endpoint>http://webservices.oorsprong.org/websamples.countryinfo/CountryInfoService.wso</con:endpoint><con:request><![CDATA[<soapenv:Envelope xmlns:soapenv="http://schemas.xmlsoap.org/soap/envelope/" xmlns:web="http://www.oorsprong.org/websamples.countryinfo">\r
   <soapenv:Header/>\r
   <soapenv:Body>\r
      <web:ListOfCurrenciesByName/>\r
   </soapenv:Body>\r
</soapenv:Envelope>]]></con:request><con:jmsConfig JMSDeliveryMode="PERSISTENT"/><con:wsaConfig mustUnderstand="NONE" version="200508" action="http://www.oorsprong.org/websamples.countryinfo/CountryInfoServiceSoapType/ListOfCurrenciesByNameRequest"/></con:call></con:operation><con:operation id="b629b46d-fc70-4ea6-94bd-35c1a69f540a" isOneWay="false" action="" name="ListOfLanguagesByCode" bindingOperationName="ListOfLanguagesByCode" type="Request-Response" inputName="" receivesAttachments="false" sendsAttachments="false" anonymous="optional"><con:settings/><con:call id="327b09cd-bcb4-474d-ac10-d6a9bbd6f158" name="Request 1"><con:settings/><con:encoding>UTF-8</con:encoding><con:endpoint>http://webservices.oorsprong.org/websamples.countryinfo/CountryInfoService.wso</con:endpoint><con:request><![CDATA[<soapenv:Envelope xmlns:soapenv="http://schemas.xmlsoap.org/soap/envelope/" xmlns:web="http://www.oorsprong.org/websamples.countryinfo">\r
   <soapenv:Header/>\r
   <soapenv:Body>\r
      <web:ListOfLanguagesByCode/>\r
   </soapenv:Body>\r
</soapenv:Envelope>]]></con:request><con:jmsConfig JMSDeliveryMode="PERSISTENT"/><con:wsaConfig mustUnderstand="NONE" version="200508" action="http://www.oorsprong.org/websamples.countryinfo/CountryInfoServiceSoapType/ListOfLanguagesByCodeRequest"/></con:call></con:operation><con:operation id="fc84639c-5a62-42e5-8da9-b1376cd7bbf2" isOneWay="false" action="" name="ListOfLanguagesByName" bindingOperationName="ListOfLanguagesByName" type="Request-Response" inputName="" receivesAttachments="false" sendsAttachments="false" anonymous="optional"><con:settings/><con:call id="fe59d850-b971-4200-b304-6adf7e4dc0cd" name="Request 1"><con:settings/><con:encoding>UTF-8</con:encoding><con:endpoint>http://webservices.oorsprong.org/websamples.countryinfo/CountryInfoService.wso</con:endpoint><con:request><![CDATA[<soapenv:Envelope xmlns:soapenv="http://schemas.xmlsoap.org/soap/envelope/" xmlns:web="http://www.oorsprong.org/websamples.countryinfo">\r
   <soapenv:Header/>\r
   <soapenv:Body>\r
      <web:ListOfLanguagesByName/>\r
   </soapenv:Body>\r
</soapenv:Envelope>]]></con:request><con:jmsConfig JMSDeliveryMode="PERSISTENT"/><con:wsaConfig mustUnderstand="NONE" version="200508" action="http://www.oorsprong.org/websamples.countryinfo/CountryInfoServiceSoapType/ListOfLanguagesByNameRequest"/></con:call></con:operation></con:interface><con:testSuite id="4f8f4ec7-cb75-4495-b020-facbad8e9cdb" name="TestSuite"><con:settings/><con:runType>SEQUENTIAL</con:runType><con:testCase id="b19db7fc-535a-4a4b-b56f-fd09c3d8015a" failOnError="true" failTestCaseOnErrors="true" keepSession="false" maxResults="0" name="TestCase" searchProperties="true"><con:settings/><con:setupScript>log.info("before load from desktstop")</con:setupScript><con:tearDownScript>log.info("after load from deskstop")</con:tearDownScript><con:properties/></con:testCase><con:testCase id="c3041817-bb94-44df-aabd-9bcbd4d4992e" failOnError="true" failTestCaseOnErrors="true" keepSession="false" maxResults="0" name="TestCase_Assertion" searchProperties="true"><con:settings/><con:testStep type="request" id="bd26e3aa-8869-4e52-9d33-ab0862d6c070" name="CountryCurrency"><con:settings/><con:config xsi:type="con:RequestStep" xmlns:xsi="http://www.w3.org/2001/XMLSchema-instance"><con:interface>CountryInfoServiceSoapBinding</con:interface><con:operation>CountryCurrency</con:operation><con:request name="CountryCurrency" id="148df37f-994b-4d1f-8392-c55d307926e3"><con:settings><con:setting id="com.eviware.soapui.impl.wsdl.WsdlRequest@request-headers">&lt;xml-fragment/></con:setting></con:settings><con:encoding>UTF-8</con:encoding><con:endpoint>http://webservices.oorsprong.org/websamples.countryinfo/CountryInfoService.wso</con:endpoint><con:request><![CDATA[<soapenv:Envelope xmlns:soapenv="http://schemas.xmlsoap.org/soap/envelope/" xmlns:web="http://www.oorsprong.org/websamples.countryinfo">\r
   <soapenv:Header/>\r
   <soapenv:Body>\r
      <web:CountryCurrency>\r
         <web:sCountryISOCode>IN</web:sCountryISOCode>\r
      </web:CountryCurrency>\r
   </soapenv:Body>\r
</soapenv:Envelope>]]></con:request><con:assertion type="Simple Contains" id="27d4fce2-0530-408b-b756-6133c787cbae" name="Contains"><con:configuration><token>INR</token><ignoreCase>false</ignoreCase><useRegEx>false</useRegEx></con:configuration></con:assertion><con:assertion type="Invalid HTTP Status Codes" id="7f14c998-41b1-4f3b-a8ae-d69b1a397e5e" name="Invalid HTTP Status Codes"><con:configuration><codes>401,400</codes></con:configuration></con:assertion><con:assertion type="GroovyScriptAssertion" id="f29eb270-c9f5-4c6d-97f2-9ec1c5007799" name="Script Assertion"><con:configuration/></con:assertion><con:assertion type="Simple NotContains" id="2c8e43b0-8bee-497c-a30e-94d66ab015a1" name="Not Contains"><con:configuration><token/><ignoreCase>false</ignoreCase><useRegEx>false</useRegEx></con:configuration></con:assertion><con:assertion type="XPath Match" id="df97dd1c-f9e4-4721-a351-1c7962753b1a" name="XPath Match"><con:configuration><path>declare namespace soap='http://schemas.xmlsoap.org/soap/envelope/';
declare namespace m='http://www.oorsprong.org/websamples.countryinfo';
//*:sName</path><content>Rupees</content><allowWildcards>false</allowWildcards><ignoreNamspaceDifferences>false</ignoreNamspaceDifferences><ignoreComments>false</ignoreComments></con:configuration></con:assertion><con:assertion type="XPath Match" id="6b82a2e4-9e79-4276-9cf7-92d13459a159" name="XPath Match 1"><con:configuration/></con:assertion><con:assertion type="XQuery Match" id="b971d6f8-feeb-4c04-87e6-8e5dc6c3e8a8" name="XQuery Match"><con:configuration><path>declare namespace soap='http://schemas.xmlsoap.org/soap/envelope/';
declare namespace m='http://www.oorsprong.org/websamples.countryinfo';
//m:sISOCode</path><content>&lt;m:sISOCode xmlns:m="http://www.oorsprong.org/websamples.countryinfo">INR&lt;/m:sISOCode></content><allowWildcards>false</allowWildcards><ignoreNamspaceDifferences>false</ignoreNamspaceDifferences><ignoreComments>false</ignoreComments></con:configuration></con:assertion><con:assertion type="Schema Compliance" id="3ecc0e55-289f-4ec7-9959-7745160db623" name="Schema Compliance"><con:configuration><definition/></con:configuration></con:assertion><con:assertion type="SOAP Response" id="c9624b2a-1b95-4706-98ff-a76cd2b0d64b" name="SOAP Response"/><con:assertion type="SOAP Fault Assertion" id="e4cd1b20-06a4-4c6b-bb3c-1f936623b15c" name="Not SOAP Fault"/><con:assertion type="GroovyScriptAssertion" id="934ad9c7-9550-435d-a3f6-6fd0cc6a8dd5" name="Script Assertion 1"><con:configuration/></con:assertion><con:assertion type="Response SLA Assertion" id="010bb163-b62b-4d43-a165-f960d6986473" name="Response SLA"><con:configuration><SLA>5000</SLA></con:configuration></con:assertion><con:assertion type="Sensitive Information Exposure" id="318efcfd-0792-4c27-9c36-2ea9bd5e904b" name="Sensitive Information Exposure"><con:configuration/></con:assertion><con:assertion type="GroovyScriptAssertion" id="07097903-f571-4522-982f-0be811c9715a" name="Script Assertion_Time_Checking"><con:configuration><scriptText>     // Response Time Checking
 assert messageExchange.timeTaken&lt;2000</scriptText></con:configuration></con:assertion><con:assertion type="GroovyScriptAssertion" id="61fedfdf-10b0-488d-a5f6-5f6bcfbd699e"><con:configuration/></con:assertion><con:assertion type="GroovyScriptAssertion" id="40342595-d038-4f12-bd64-9099266b6490" name="Script Assertion_End_PointURL"><con:configuration><scriptText>def endpoint="http://webservices.oorsprong.org/websamples.countryinfo/CountryInfoService.wso"
 assert messageExchange.getEndpoint()==endpoint</scriptText></con:configuration></con:assertion><con:credentials><con:authType>No Authorization</con:authType></con:credentials><con:jmsConfig JMSDeliveryMode="PERSISTENT"/><con:jmsPropertyConfig/><con:wsaConfig action="http://www.oorsprong.org/websamples.countryinfo/CountryInfoServiceSoapType/CountryCurrencyRequest" mustUnderstand="NONE" version="200508"/><con:wsrmConfig version="1.2"/></con:request></con:config></con:testStep><con:testStep type="restrequest" name="GetCountryByName" id="a20396e5-62ff-4c3b-85c4-7348ebd2d221"><con:settings/><con:config service="https://restcountries.eu" resourcePath="/rest/v2/name/India/{fullText}" methodName="Contains_India" xsi:type="con:RestRequestStep" xmlns:xsi="http://www.w3.org/2001/XMLSchema-instance"><con:restRequest name="GetCountryByName" id="12c5791b-097b-49d2-be90-2bbd7357f052" mediaType="application/json"><con:settings><con:setting id="com.eviware.soapui.impl.wsdl.WsdlRequest@request-headers">&lt;xml-fragment/></con:setting></con:settings><con:endpoint>https://restcountries.eu</con:endpoint><con:request/><con:originalUri>https://restcountries.eu/rest/v2/name/aruba</con:originalUri><con:assertion type="Response SLA Assertion" id="c349a32d-8767-4690-b44f-23f5f6f83036" name="Response SLA"><con:configuration><SLA>50000</SLA></con:configuration></con:assertion><con:assertion type="GroovyScriptAssertion" id="55945ab8-ac5d-472a-b85f-4c95718d77fc" name="Script Assertion"><con:configuration/></con:assertion><con:assertion type="Sensitive Information Exposure" id="3182b6dc-1848-4bdb-bb52-6372360431a8" name="Sensitive Information Exposure"><con:configuration/></con:assertion><con:assertion type="JsonPath Match" id="ae83350d-f824-4386-b69e-1f970fc1c40f" name="JsonPath Match"><con:configuration><path>[1].languages[0].name</path><content>Hindi</content><allowWildcards>false</allowWildcards><ignoreNamspaceDifferences>false</ignoreNamspaceDifferences><ignoreComments>false</ignoreComments></con:configuration></con:assertion><con:assertion type="JsonPath RegEx Match" id="7ea48543-9032-4788-9181-4de4928503a3" name="JsonPath RegEx Match"><con:configuration><path>[1].languages[0].name</path><content>true</content><allowWildcards>false</allowWildcards><ignoreNamspaceDifferences>false</ignoreNamspaceDifferences><ignoreComments>false</ignoreComments><regEx>Hindi</regEx></con:configuration></con:assertion><con:credentials><con:authType>No Authorization</con:authType></con:credentials><con:jmsConfig JMSDeliveryMode="PERSISTENT"/><con:jmsPropertyConfig/><con:parameters/><con:parameterOrder><con:entry>fullText</con:entry></con:parameterOrder></con:restRequest></con:config></con:testStep><con:setupScript>log.info("before load from desktstop")</con:setupScript><con:tearDownScript>log.info("after load from deskstop")</con:tearDownScript><con:properties/></con:testCase><con:properties/></con:testSuite><con:properties/><con:afterLoadScript>// if create file in smartbear bin use name only 
//otherwise path of file \  >> only for window
//   / >> any environment it support
def su=new File ("C:/Users/home/Desktop/setup.txt").text
def td=new File ("C:/Users/home/Desktop/setupdown.txt").text
project.getTestSuiteList().each{testSuite ->
testSuite.getTestCaseList().each{testCase ->
testCase.setSetupScript(su)
testCase.setTearDownScript(td)
}
}


</con:afterLoadScript><con:wssContainer/><con:oAuth2ProfileContainer/><con:oAuth1ProfileContainer/><con:beforeRunScript>log.info("project_level_Setup_Script_before Runn")</con:beforeRunScript><con:afterRunScript>log.info("project_level_Tear_Down_AFter_Run Script")</con:afterRunScript><con:sensitiveInformation/></con:soapui-project>